{
  "first_used_card_id": "27a1b68218a47eb6ece2072efeb0b80cc05eb1c914f6b7a4a826b4f52287c903",
  "formal_definition": "The organising framework of Policy Statement 2.0 on the Development of Digital Assets in Hong Kong, issued 26 June 2025.",
  "generated_at": "2026-07-09T07:03:38Z",
  "id": "leap-framework",
  "jurisdictions": [
    "hk"
  ],
  "model": "not recorded (pre-provenance content)",
  "plain_definition": "The Hong Kong Government's name for its four-part digital-asset policy agenda: Legal and regulatory streamlining, Expanding tokenised products, Advancing use cases and cross-sectoral collaboration, and People and partnership development.",
  "related_terms": [
    "policy-statement-2.0",
    "tokenisation"
  ],
  "schema_version": 2,
  "status": "unverified",
  "term": "LEAP framework"
}
